streamfield_tools/__init__.py
streamfield_tools/apps.py
streamfield_tools/fields.py
streamfield_tools/registry.py
streamfield_tools/blocks/__init__.py
streamfield_tools/blocks/base.py
streamfield_tools/blocks/field_block.py
streamfield_tools/blocks/image_chooser_block.py
streamfield_tools/blocks/list_block.py
streamfield_tools/blocks/stream_block.py
streamfield_tools/blocks/struct_block.py
streamfield_tools/templatetags/__init__.py
streamfield_tools/templatetags/renditionaware_image_tags.py
tests/__init__.py
tests/blocks.py
tests/models.py
tests/registered_blocks.py
tests/test_settings.py
tests/tests.py
tests/urls.py
tests/test_exception_alreadyregistered/__init__.py
tests/test_exception_alreadyregistered/registered_blocks.py
tests/test_exception_invalidblock/__init__.py
tests/test_exception_invalidblock/registered_blocks.py
tests/test_exception_notregistered/__init__.py
tests/test_exception_notregistered/registered_blocks.py
tests/test_find_blocks/__init__.py
tests/test_find_blocks/registered_blocks.py
tests/test_unregister_block/__init__.py
tests/test_unregister_block/registered_blocks.py
wagtail_streamfieldtools-0.3.dist-info/DESCRIPTION.rst
wagtail_streamfieldtools-0.3.dist-info/LICENSE.txt
wagtail_streamfieldtools-0.3.dist-info/METADATA
wagtail_streamfieldtools-0.3.dist-info/RECORD
wagtail_streamfieldtools-0.3.dist-info/WHEEL
wagtail_streamfieldtools-0.3.dist-info/metadata.json
wagtail_streamfieldtools-0.3.dist-info/top_level.txt
