Metadata-Version: 2.0
Name: wagtail-streamfieldtools
Version: 0.3
Summary: A suite of tools that extends Wagtail's already-awesome StreamField to make it even more flexible/versatile/useful!
Home-page: http://github.com/WGBH/wagtail-streamfieldtools/
Author: Jonathan Ellenberger
Author-email: jonathan_ellenberger@wgbh.org
License: MIT License, see LICENSE
Platform: UNKNOWN
Classifier: Framework :: Django
Classifier: Framework :: Django :: 1.8
Classifier: Framework :: Django :: 1.9
Classifier: License :: OSI Approved :: MIT License
Classifier: Natural Language :: English
Classifier: Programming Language :: Python
Classifier: Programming Language :: Python :: 2
Classifier: Programming Language :: Python :: 2.7
Classifier: Programming Language :: Python :: 3
Classifier: Programming Language :: Python :: 3.4
Classifier: Programming Language :: Python :: 3.5
Classifier: Development Status :: 3 - Alpha
Requires-Dist: wagtail (>=1.2)
